yt_core/_BaseClass.py
yt_core/_Comments.py
yt_core/_Search.py
yt_core/_Video.py
yt_core/__init__.py
yt_core/__main__.py
yt_core/_helper.py
yt_core/helper.py
yt_core/_dl/__init__.py
yt_core/_dl/_download.py
yt_core/_dl/api.py
yt_core/_dl/comments.py
yt_core/_dl/localization.py
yt_core/_dl/search.py
yt_core/_dl/trending.py
yt_core/_dl/video.py
yt_core_ralf1307-0.1.4.dist-info/COPYING
yt_core_ralf1307-0.1.4.dist-info/METADATA
yt_core_ralf1307-0.1.4.dist-info/WHEEL
yt_core_ralf1307-0.1.4.dist-info/top_level.txt
yt_core_ralf1307-0.1.4.dist-info/RECORD
