Metadata-Version: 2.1
Name: yt-core-ralf1307
Version: 0.1.4
Summary: YT_Core provides easy access to Youtube
Home-page: https://gitlab.com/ralf1307/ytcore
Author: "Ralf Rachinger"
Author-email: ralfrachinger@gmail.com
License: AGPLv3+
Platform: UNKNOWN
Classifier: Programming Language :: Python :: 3
Classifier: License :: OSI Approved :: GNU Affero General Public License v3 or later (AGPLv3+)
Classifier: Operating System :: OS Independent
Classifier: Development Status :: 2 - Pre-Alpha
Requires-Python: >=3.8
Requires-Dist: requests
Requires-Dist: importlib
